nrcan_etl_toolbox/__init__.py
nrcan_etl_toolbox/database/__init__.py
nrcan_etl_toolbox/database/database_connection_config.py
nrcan_etl_toolbox/database/interface/__init__.py
nrcan_etl_toolbox/database/interface/abstract_database_objects_handlers.py
nrcan_etl_toolbox/database/orm/__init__.py
nrcan_etl_toolbox/database/orm/base/__init__.py
nrcan_etl_toolbox/database/orm/base/base_table_mapping.py
nrcan_etl_toolbox/etl_logging/__init__.py
nrcan_etl_toolbox/etl_logging/etl_logger.py
nrcan_etl_toolbox/etl_toolbox/__init__.py
nrcan_etl_toolbox/etl_toolbox/data_downloader/__init__.py
nrcan_etl_toolbox/etl_toolbox/data_downloader/ftp/__init__.py
nrcan_etl_toolbox/etl_toolbox/data_downloader/ftp/ftp_downloader.py
nrcan_etl_toolbox/etl_toolbox/reader/__init__.py
nrcan_etl_toolbox/etl_toolbox/reader/reader_factory.py
nrcan_etl_toolbox/etl_toolbox/reader/source_readers/__init__.py
nrcan_etl_toolbox/etl_toolbox/reader/source_readers/base_reader.py
nrcan_etl_toolbox/etl_toolbox/reader/source_readers/csv_reader.py
nrcan_etl_toolbox/etl_toolbox/reader/source_readers/excel_reader.py
nrcan_etl_toolbox/etl_toolbox/reader/source_readers/geopackage_reader.py
nrcan_etl_toolbox/etl_toolbox/reader/source_readers/json_reader.py
nrcan_etl_toolbox/etl_toolbox/reader/source_readers/postgis_reader.py
nrcan_etl_toolbox/etl_toolbox/reader/source_readers/shapefile_reader.py
nrcan_etl_toolbox-0.2.15.dist-info/METADATA
nrcan_etl_toolbox-0.2.15.dist-info/WHEEL
nrcan_etl_toolbox-0.2.15.dist-info/licenses/LICENSE
nrcan_etl_toolbox-0.2.15.dist-info/RECORD
