Metadata-Version: 2.4
Name: nrcan-etl-toolbox
Version: 0.2.15
Summary: Package for logging and database interfacing using SQLAlchemy and SQLModels
License: MIT License
License-File: LICENSE
Author: Xavier Malet
Author-email: xavier.malet@nrcan-rncan.gc.ca
Requires-Python: >=3.10,<4
Classifier: License :: Other/Proprietary License
Classifier: Programming Language :: Python :: 3
Classifier: Programming Language :: Python :: 3.10
Classifier: Programming Language :: Python :: 3.11
Classifier: Programming Language :: Python :: 3.12
Classifier: Programming Language :: Python :: 3.13
Classifier: Programming Language :: Python :: 3.14
Requires-Dist: SQLAlchemy (>2.0.40)
Requires-Dist: fiona (>=1.10.1)
Requires-Dist: geoalchemy2 (>0.17.1)
Requires-Dist: geopandas
Requires-Dist: omegaconf (>=2.3.0)
Requires-Dist: openpyxl (>=3.1.5)
Requires-Dist: pandas
Requires-Dist: paramiko (>=3.5.1)
Requires-Dist: psycopg2-binary (>2.9.10)
Requires-Dist: pytest (>=8.0.0)
Requires-Dist: python-dotenv
Requires-Dist: ruff (>=0.11.10)
Requires-Dist: shapely
Requires-Dist: sqlmodel (>0.0.25)
Requires-Dist: tqdm (>=4.67.1)
